aws_codestarconnection/__init__.py
aws_codestarconnection/py.typed
aws_codestarconnection/_jsii/__init__.py
aws_codestarconnection/_jsii/aws-codestarconnection@0.0.13.jsii.tgz
aws_codestarconnection-0.0.13.dist-info/LICENSE
aws_codestarconnection-0.0.13.dist-info/METADATA
aws_codestarconnection-0.0.13.dist-info/WHEEL
aws_codestarconnection-0.0.13.dist-info/top_level.txt
aws_codestarconnection-0.0.13.dist-info/RECORD
