Metadata-Version: 2.1
Name: aws-codestarconnection
Version: 0.0.13
Summary: AWS CDK L2 construct for aws code star connection
Home-page: https://github.com/JumpToTheCloud/aws-codestarconnection
Author: Antonio Márquez Pérez<antonio.marquez@jumptothecloud.tech>
License: Apache-2.0
Project-URL: Source, https://github.com/JumpToTheCloud/aws-codestarconnection
Classifier: Intended Audience :: Developers
Classifier: Operating System :: OS Independent
Classifier: Programming Language :: JavaScript
Classifier: Programming Language :: Python :: 3 :: Only
Classifier: Programming Language :: Python :: 3.8
Classifier: Programming Language :: Python :: 3.9
Classifier: Programming Language :: Python :: 3.10
Classifier: Programming Language :: Python :: 3.11
Classifier: Typing :: Typed
Classifier: Development Status :: 5 - Production/Stable
Classifier: License :: OSI Approved
Requires-Python: ~=3.8
License-File: LICENSE
Requires-Dist: aws-cdk-lib <3.0.0,>=2.122.0
Requires-Dist: constructs <11.0.0,>=10.3.0
Requires-Dist: jsii <2.0.0,>=1.94.0
Requires-Dist: publication >=0.0.3
Requires-Dist: typeguard ~=2.13.3
